[
  {
    "id": "White Scar",
    "paint_name": "White Scar",
    "company": "Citadel",
    "hex_color": "FFFFFF",
    "color_conversions": [
      "Skull White 1",
      "Dead White",
      "White",
      "Arctic White",
      "Eternal White",
      "Pure White",
      "Morrow white",
      "White",
      "Matt White",
      "White Matt"
    ],
    "category":  "paints"
  },
  {
    "id": "Dead White",
    "paint_name": "Dead White",
    "company": "Vallejo",
    "hex_color": "FFFFFF",
    "color_conversions": [
      "Skull White 1",
      "White Scar",
      "White",
      "Arctic White",
      "Eternal White",
      "Pure White",
      "Morrow white",
      "White",
      "Matt White",
      "White Matt"
    ],
    "category": "paints"
  }
]
